iy/__init__.py
iy/dummy.py
iy/ifinal.py
iy/itsext.py
iy/iy.py
iy/questions.py
iy/version.py
iy/yt.py
you_dl-1.4.1.dist-info/LICENSE
you_dl-1.4.1.dist-info/METADATA
you_dl-1.4.1.dist-info/WHEEL
you_dl-1.4.1.dist-info/entry_points.txt
you_dl-1.4.1.dist-info/top_level.txt
you_dl-1.4.1.dist-info/RECORD
