Metadata-Version: 2.1
Name: you-dl
Version: 1.4.1
Summary: A simple interactive youtube downloader written in python. Interactively select the quality and format for youtube-dl
Home-page: https://github.com/xvishaldongre/you-dl
Author: vishal dongre
Author-email: xvishaldongre@gmail.com
License: GPLv3
Platform: UNKNOWN
Classifier: Programming Language :: Python :: 3
Classifier: License :: OSI Approved :: GNU General Public License v3 (GPLv3)
Classifier: Operating System :: OS Independent
Classifier: Environment :: Console
Classifier: Topic :: Multimedia 
Requires-Python: >=3.5
Requires-Dist: PyInquirer
Requires-Dist: click
Requires-Dist: halo
Requires-Dist: humanfriendly
Requires-Dist: pafy
Requires-Dist: prompt-toolkit (==1.0.14)
Requires-Dist: pyfiglet
Requires-Dist: pyperclip
Requires-Dist: regex
Requires-Dist: rich
Requires-Dist: youtube-dl
Requires-Dist: youtube-search-python
